{
  "params": {
    "pred_dir": "previsoes/predlen_loss_todos_ativos/retornos/AttentionSoloChannelIndependentShrINSpec/lookback_32/pred_len_10/_backtest_janelas_only",
    "price_path": "data/b3_daily_tfb.csv",
    "model_output": "returns",
    "rebalance_k": 1,
    "max_assets": 9,
    "horizon": 1,
    "only_positive_pred": true,
    "returns_mode": "step",
    "annual_rf": 0.043
  },
  "metrics": {
    "total_return": -0.5012532756515464,
    "annual_return": -0.26878342825568835,
    "annual_vol": 0.21372460547994127,
    "sharpe": -1.4588092351629125,
    "max_drawdown": -0.5391070512071757,
    "mean_precision_positive": 0.47063492063492063,
    "mean_spearman_ic": -0.04581607597121532,
    "icir": -0.3161474974723648,
    "mean_n_assets": 9.0,
    "n_periods": 560
  }
}