{
  "params": {
    "pred_dir": "previsoes/financeiro/prices/TransformerShrINSpec/lookback_246/pred_len_20/_backtest_janelas_only",
    "price_path": "data/b3_daily_financeiro.csv",
    "model_output": "prices",
    "rebalance_k": 20,
    "max_assets": 9,
    "horizon": 20,
    "only_positive_pred": true,
    "returns_mode": "step",
    "annual_rf": 0.043
  },
  "metrics": {
    "total_return": 0.31550968877956964,
    "annual_return": 0.13133786524858881,
    "annual_vol": 0.2675626883869945,
    "sharpe": 0.330157638126358,
    "max_drawdown": -0.21945669531183243,
    "mean_precision_positive": 0.5833333333333333,
    "mean_spearman_ic": -0.09523809523809523,
    "icir": -0.18410235581579393,
    "mean_n_assets": 4.142857142857143,
    "n_periods": 28
  }
}