{
  "params": {
    "pred_dir": "previsoes/predlen_loss_todos_ativos/prices/TransformerShrINSpec/lookback_104/pred_len_10/_backtest_janelas_only",
    "price_path": "data/b3_daily_tfb.csv",
    "model_output": "prices",
    "rebalance_k": 5,
    "max_assets": 9,
    "horizon": 5,
    "only_positive_pred": true,
    "returns_mode": "step",
    "annual_rf": 0.043
  },
  "metrics": {
    "total_return": 0.16480637183826552,
    "annual_return": 0.07106094107946137,
    "annual_vol": 0.308850293162417,
    "sharpe": 0.09085612576933767,
    "max_drawdown": -0.35820179008022446,
    "mean_precision_positive": 0.4851190476190476,
    "mean_spearman_ic": -0.048135607543342555,
    "icir": -0.2587942312973164,
    "mean_n_assets": 9.0,
    "n_periods": 112
  }
}