{
  "params": {
    "pred_dir": "previsoes/predlen_loss_todos_ativos/log_retornos/AttentionSoloChannelIndependentShrINSpec/lookback_104/pred_len_5/_backtest_janelas_only",
    "price_path": "data/b3_daily_tfb.csv",
    "model_output": "log_returns",
    "rebalance_k": 1,
    "max_assets": 9,
    "horizon": 1,
    "only_positive_pred": true,
    "returns_mode": "step",
    "annual_rf": 0.043
  },
  "metrics": {
    "total_return": -0.2036821627021137,
    "annual_return": -0.09659434804126232,
    "annual_vol": 0.20107535108667254,
    "sharpe": -0.6942389869611161,
    "max_drawdown": -0.2863833786557354,
    "mean_precision_positive": 0.4658800393313668,
    "mean_spearman_ic": -0.010398576611485471,
    "icir": -0.05746821912862602,
    "mean_n_assets": 9.0,
    "n_periods": 565
  }
}